rsap/AsyncRSAP.py
rsap/DisRSAP.py
rsap/RSAP.py
rsap/__init__.py
rsap/exceptions.py
rsap-2.4.2.dist-info/LICENSE
rsap-2.4.2.dist-info/METADATA
rsap-2.4.2.dist-info/WHEEL
rsap-2.4.2.dist-info/top_level.txt
rsap-2.4.2.dist-info/RECORD
