Metadata-Version: 2.1
Name: rsap
Version: 2.4.2
Summary: A simple wrapper for the Random Stuff API
Home-page: https://github.com/Hunter2807/RSAP
Author: Hunter
License: UNKNOWN
Platform: UNKNOWN
Classifier: Natural Language :: English
Classifier: Intended Audience :: Developers
Classifier: Natural Language :: English
Classifier: Operating System :: MacOS
Classifier: Operating System :: Microsoft :: Windows
Classifier: Programming Language :: Python :: 3.7
Classifier: Programming Language :: Python :: 3.8
Classifier: Programming Language :: Python :: 3.9
Requires-Python: >3.6
Requires-Dist: discord.py
Requires-Dist: aiohttp
Requires-Dist: requests
